mcp_shell_server/__init__.py
mcp_shell_server/command_preprocessor.py
mcp_shell_server/command_validator.py
mcp_shell_server/directory_manager.py
mcp_shell_server/io_redirection_handler.py
mcp_shell_server/process_manager.py
mcp_shell_server/server.py
mcp_shell_server/shell_executor.py
mcp_shell_server/version.py
mcp_log_search_server-0.1.4.dist-info/METADATA
mcp_log_search_server-0.1.4.dist-info/WHEEL
mcp_log_search_server-0.1.4.dist-info/entry_points.txt
mcp_log_search_server-0.1.4.dist-info/licenses/LICENSE
mcp_log_search_server-0.1.4.dist-info/RECORD
