Metadata-Version: 2.4
Name: mcp-log-search-server
Version: 0.1.4
Summary: MCP Log Search Server - Intelligent log analysis and search via MCP protocol
Author: canc3s
License: MIT
License-File: LICENSE
Requires-Python: >=3.11
Requires-Dist: asyncio>=3.4.3
Requires-Dist: mcp>=1.1.2
Provides-Extra: dev
Requires-Dist: black>=23.3.0; extra == 'dev'
Requires-Dist: isort>=5.12.0; extra == 'dev'
Requires-Dist: mypy>=1.2.0; extra == 'dev'
Requires-Dist: pre-commit>=3.2.2; extra == 'dev'
Requires-Dist: ruff>=0.0.262; extra == 'dev'
